LICENSE
README.md
setup.py
algo_fun/__init__.py
algo_fun/get_bfs_traversal_order.py
algo_fun_bfs_traversal_order.egg-info/PKG-INFO
algo_fun_bfs_traversal_order.egg-info/SOURCES.txt
algo_fun_bfs_traversal_order.egg-info/dependency_links.txt
algo_fun_bfs_traversal_order.egg-info/top_level.txt
tests/__init__.py
tests/test_get_bfs_traversal_order.py