Metadata-Version: 2.1
Name: algo-fun-bfs-traversal-order
Version: 0.1.0
Summary: get the bfs traversal order of a given graph
Home-page: https://gitlab.com/ChristopheLagaillarde/algo_fun_bfs_traversal_order
Author: Christophe Lagaillarde
Author-email: chrislag94@gmail.com
License: MIT
License-File: LICENSE
